odoo/addons/beesdoo_website_shift/README.rst
odoo/addons/beesdoo_website_shift/__init__.py
odoo/addons/beesdoo_website_shift/__manifest__.py
odoo/addons/beesdoo_website_shift/controllers/__init__.py
odoo/addons/beesdoo_website_shift/controllers/main.py
odoo/addons/beesdoo_website_shift/controllers/portal.py
odoo/addons/beesdoo_website_shift/controllers/shift_grid_utils.py
odoo/addons/beesdoo_website_shift/data/res_config_data.xml
odoo/addons/beesdoo_website_shift/i18n/beesdoo_website_shift.pot
odoo/addons/beesdoo_website_shift/i18n/fr_BE.po
odoo/addons/beesdoo_website_shift/i18n/nl_BE.po
odoo/addons/beesdoo_website_shift/migrations/12.0.2.2.0/post-set_share_supercoop_info.py
odoo/addons/beesdoo_website_shift/models/__init__.py
odoo/addons/beesdoo_website_shift/models/res_config.py
odoo/addons/beesdoo_website_shift/models/res_partner.py
odoo/addons/beesdoo_website_shift/models/website.py
odoo/addons/beesdoo_website_shift/readme/CONTRIBUTORS.rst
odoo/addons/beesdoo_website_shift/readme/DESCRIPTION.rst
odoo/addons/beesdoo_website_shift/static/description/index.html
odoo/addons/beesdoo_website_shift/static/src/js/script.js
odoo/addons/beesdoo_website_shift/views/assets.xml
odoo/addons/beesdoo_website_shift/views/my_shift_website_templates.xml
odoo/addons/beesdoo_website_shift/views/portal_website_templates.xml
odoo/addons/beesdoo_website_shift/views/res_config_views.xml
odoo/addons/beesdoo_website_shift/views/res_partner_views.xml
odoo/addons/beesdoo_website_shift/views/shift_website_templates.xml
odoo12_addon_beesdoo_website_shift-12.0.2.2.0.99.dev1.dist-info/METADATA
odoo12_addon_beesdoo_website_shift-12.0.2.2.0.99.dev1.dist-info/WHEEL
odoo12_addon_beesdoo_website_shift-12.0.2.2.0.99.dev1.dist-info/top_level.txt
odoo12_addon_beesdoo_website_shift-12.0.2.2.0.99.dev1.dist-info/RECORD
