Metadata-Version: 2.1
Name: odoo12-addon-beesdoo-website-shift
Version: 12.0.2.2.0.99.dev1
Summary: Show available shifts for regular and irregular workers on the website and let workers manage their shifts with an easy web interface.
Home-page: https://github.com/beescoop/Obeesdoo
Author: Coop IT Easy SC
License: AGPL-3
Platform: UNKNOWN
Classifier: Programming Language :: Python
Classifier: Framework :: Odoo
Classifier: Framework :: Odoo :: 12.0
Classifier: License :: OSI Approved :: GNU Affero General Public License v3
Requires-Python: >=3.5
Requires-Dist: odoo12-addon-shift
Requires-Dist: odoo (<12.1dev,>=12.0a)
